setup.py
dstdbn_probability/Binomialdistribution.py
dstdbn_probability/Gaussiandistribution.py
dstdbn_probability/Generaldistribution.py
dstdbn_probability/__init__.py
dstdbn_probability.egg-info/PKG-INFO
dstdbn_probability.egg-info/SOURCES.txt
dstdbn_probability.egg-info/dependency_links.txt
dstdbn_probability.egg-info/not-zip-safe
dstdbn_probability.egg-info/top_level.txt